etchrepl.py
etchrepl-0.1.5.dist-info/entry_points.txt
etchrepl-0.1.5.dist-info/WHEEL
etchrepl-0.1.5.dist-info/METADATA
etchrepl-0.1.5.dist-info/RECORD
